[ {
  "id" : "2413cde4-6cab-8b28-6138-0ba0b029e65a",
  "name" : "title",
  "label" : "Title",
  "required" : false,
  "locked" : false,
  "validation_regex" : "",
  "allow_new_line" : false,
  "show_emoji_picker" : false,
  "type" : "text",
  "default" : "HUBSPOT REVOPS SPECIALISTS"
}, {
  "id" : "eda84b6c-4b26-1c15-620a-bcd3e932023a",
  "name" : "sub_text",
  "label" : "Sub Text",
  "required" : false,
  "locked" : false,
  "type" : "richtext",
  "default" : "<p>Process Strategy + Highly Technical Implementation + <br>Customized Training.</p>"
}, {
  "id" : "38100a9c-db98-57a4-eae2-2cbdbbcf784d",
  "name" : "button_text",
  "label" : "Button Text",
  "required" : false,
  "locked" : false,
  "validation_regex" : "",
  "allow_new_line" : false,
  "show_emoji_picker" : false,
  "type" : "text",
  "default" : "LET’S TALK HUBSPOT!"
}, {
  "id" : "8df390c0-257d-7b3b-72d3-29114787fded",
  "name" : "button_link",
  "label" : "Button Link",
  "required" : false,
  "locked" : false,
  "supported_types" : [ "EXTERNAL", "CONTENT", "FILE", "EMAIL_ADDRESS", "BLOG" ],
  "show_advanced_rel_options" : false,
  "type" : "link",
  "default" : {
    "url" : {
      "content_id" : null,
      "type" : "EXTERNAL",
      "href" : ""
    },
    "open_in_new_tab" : false,
    "no_follow" : false
  }
}, {
  "id" : "6bbd1abd-2320-0639-f6ba-8494d247de7f",
  "name" : "image_group",
  "label" : "image Group",
  "required" : false,
  "locked" : false,
  "occurrence" : {
    "min" : 1,
    "max" : null,
    "sorting_label_field" : null,
    "default" : 1
  },
  "children" : [ {
    "id" : "7017fd31-9993-b03d-c5d4-4a30a5d8254e",
    "name" : "image_field",
    "label" : "Image",
    "required" : false,
    "locked" : false,
    "responsive" : true,
    "resizable" : true,
    "show_loading" : true,
    "type" : "image",
    "default" : {
      "size_type" : "auto",
      "src" : "https://www.remotish.agency/hubfs/Icons/Team%20Members%20Home%20Optimized/WebP/KAM.webp",
      "alt" : "KAM",
      "loading" : "lazy",
      "width" : 495,
      "height" : 585,
      "max_width" : 495,
      "max_height" : 585
    }
  } ],
  "tab" : "CONTENT",
  "expanded" : false,
  "type" : "group",
  "default" : [ {
    "image_field" : {
      "size_type" : "auto",
      "src" : "https://www.remotish.agency/hubfs/Icons/Team%20Members%20Home%20Optimized/WebP/KAM.webp",
      "alt" : "KAM",
      "loading" : "lazy",
      "width" : 495,
      "height" : 585,
      "max_width" : 495,
      "max_height" : 585
    }
  } ]
}, {
  "id" : "01a55e09-1b03-c834-065c-8502c137ddd6",
  "name" : "services_group",
  "label" : "Services Group",
  "required" : false,
  "locked" : false,
  "occurrence" : {
    "min" : 1,
    "max" : null,
    "sorting_label_field" : null,
    "default" : 3
  },
  "children" : [ {
    "id" : "7411ca07-94ab-0bc8-a75f-3e53571b3a3a",
    "name" : "icon_image",
    "label" : "Icon Image(Color)",
    "required" : false,
    "locked" : false,
    "responsive" : true,
    "resizable" : true,
    "show_loading" : true,
    "type" : "image",
    "default" : {
      "size_type" : "auto",
      "src" : "https://www.remotish.agency/hubfs/Group%2015.svg",
      "alt" : "Group 15",
      "loading" : "lazy",
      "width" : 88,
      "height" : 86,
      "max_width" : 88,
      "max_height" : 86
    }
  }, {
    "id" : "80e824b6-8242-90a5-95d9-c7c14cc3fe64",
    "name" : "image_icon_white_",
    "label" : "Hover  Icon (Hover White)",
    "required" : false,
    "locked" : false,
    "responsive" : true,
    "resizable" : true,
    "show_loading" : true,
    "type" : "image",
    "default" : {
      "size_type" : "auto",
      "src" : "https://www.remotish.agency/hubfs/Imported%20images/CMO%20Homepage%20Desktop.svg",
      "alt" : "CMO Homepage Desktop",
      "loading" : "lazy",
      "width" : 89,
      "height" : 88,
      "max_width" : 89,
      "max_height" : 88
    }
  }, {
    "id" : "31146c84-ac9b-015b-8228-5c817d57badf",
    "name" : "richtext_field",
    "label" : "Rich text",
    "required" : false,
    "locked" : false,
    "type" : "richtext",
    "default" : "<h3>SALES OPS</h3>\n<p>We use HubSpot to develop Allstars that efficiently generate more revenue through processes &amp; tools.</p>"
  }, {
    "id" : "ad25bf7b-bfe2-cdf1-533c-8d4c1baf602d",
    "name" : "button_text",
    "label" : "Button Text",
    "required" : false,
    "locked" : false,
    "validation_regex" : "",
    "allow_new_line" : false,
    "show_emoji_picker" : false,
    "type" : "text",
    "default" : "Read More"
  }, {
    "id" : "730f7761-60cf-14d2-00c6-4cffc9f60b68",
    "name" : "link_field",
    "label" : "Link",
    "required" : false,
    "locked" : false,
    "supported_types" : [ "EXTERNAL", "CONTENT", "FILE", "EMAIL_ADDRESS", "BLOG" ],
    "show_advanced_rel_options" : false,
    "type" : "link",
    "default" : {
      "url" : {
        "content_id" : null,
        "type" : "EXTERNAL",
        "href" : ""
      },
      "open_in_new_tab" : false,
      "no_follow" : false
    }
  } ],
  "tab" : "CONTENT",
  "expanded" : false,
  "type" : "group",
  "default" : [ {
    "icon_image" : {
      "size_type" : "auto",
      "src" : "https://www.remotish.agency/hubfs/Group%2015.svg",
      "alt" : "Group 15",
      "loading" : "lazy",
      "width" : 88,
      "height" : 86,
      "max_width" : 88,
      "max_height" : 86
    },
    "image_icon_white_" : {
      "size_type" : "auto",
      "src" : "https://www.remotish.agency/hubfs/Imported%20images/CMO%20Homepage%20Desktop.svg",
      "alt" : "CMO Homepage Desktop",
      "loading" : "lazy",
      "width" : 89,
      "height" : 88,
      "max_width" : 89,
      "max_height" : 88
    },
    "richtext_field" : "<h3>SALES OPS</h3>\n<p>We use HubSpot to develop Allstars that efficiently generate more revenue through processes &amp; tools.</p>",
    "button_text" : "Read More",
    "link_field" : {
      "url" : {
        "content_id" : null,
        "type" : "EXTERNAL",
        "href" : ""
      },
      "open_in_new_tab" : false,
      "no_follow" : false
    }
  }, {
    "icon_image" : {
      "size_type" : "auto",
      "src" : "https://www.remotish.agency/hubfs/Group%2015.svg",
      "alt" : "Group 15",
      "loading" : "lazy",
      "width" : 88,
      "height" : 86,
      "max_width" : 88,
      "max_height" : 86
    },
    "image_icon_white_" : {
      "size_type" : "auto",
      "src" : "https://www.remotish.agency/hubfs/Imported%20images/CMO%20Homepage%20Desktop.svg",
      "alt" : "CMO Homepage Desktop",
      "loading" : "lazy",
      "width" : 89,
      "height" : 88,
      "max_width" : 89,
      "max_height" : 88
    },
    "richtext_field" : "<h3>SALES OPS</h3>\n<p>We use HubSpot to develop Allstars that efficiently generate more revenue through processes &amp; tools.</p>",
    "button_text" : "Read More",
    "link_field" : {
      "url" : {
        "content_id" : null,
        "type" : "EXTERNAL",
        "href" : ""
      },
      "open_in_new_tab" : false,
      "no_follow" : false
    }
  }, {
    "icon_image" : {
      "size_type" : "auto",
      "src" : "https://www.remotish.agency/hubfs/Group%2015.svg",
      "alt" : "Group 15",
      "loading" : "lazy",
      "width" : 88,
      "height" : 86,
      "max_width" : 88,
      "max_height" : 86
    },
    "image_icon_white_" : {
      "size_type" : "auto",
      "src" : "https://www.remotish.agency/hubfs/Imported%20images/CMO%20Homepage%20Desktop.svg",
      "alt" : "CMO Homepage Desktop",
      "loading" : "lazy",
      "width" : 89,
      "height" : 88,
      "max_width" : 89,
      "max_height" : 88
    },
    "richtext_field" : "<h3>SALES OPS</h3>\n<p>We use HubSpot to develop Allstars that efficiently generate more revenue through processes &amp; tools.</p>",
    "button_text" : "Read More",
    "link_field" : {
      "url" : {
        "content_id" : null,
        "type" : "EXTERNAL",
        "href" : ""
      },
      "open_in_new_tab" : false,
      "no_follow" : false
    }
  } ]
}, {
  "id" : "styles",
  "name" : "styles",
  "label" : "Styles",
  "required" : false,
  "locked" : false,
  "children" : [ {
    "id" : "styles.corner",
    "name" : "corner",
    "label" : "Boxes Radius",
    "required" : false,
    "locked" : false,
    "children" : [ {
      "id" : "styles.corner.radius",
      "name" : "radius",
      "label" : "Radius",
      "required" : false,
      "locked" : false,
      "display" : "slider",
      "max" : 100,
      "step" : 1,
      "suffix" : "px",
      "type" : "number"
    } ],
    "tab" : "STYLE",
    "expanded" : false,
    "type" : "group",
    "default" : { }
  }, {
    "id" : "styles.boxes_bg",
    "name" : "boxes_bg",
    "label" : "Boxes Background",
    "required" : false,
    "locked" : false,
    "children" : [ {
      "id" : "styles.boxes_bg.bg_color",
      "name" : "bg_color",
      "label" : "Background color",
      "required" : false,
      "locked" : false,
      "type" : "color",
      "default" : {
        "color" : "#ffffff",
        "opacity" : 100
      }
    } ],
    "tab" : "STYLE",
    "expanded" : false,
    "type" : "group",
    "default" : {
      "bg_color" : {
        "color" : "#ffffff",
        "opacity" : 100
      }
    }
  }, {
    "id" : "styles.boxes_padding",
    "name" : "boxes_padding",
    "label" : "Boxes spacing",
    "required" : false,
    "locked" : false,
    "type" : "spacing",
    "default" : {
      "padding" : {
        "top" : {
          "value" : 30,
          "units" : "px"
        },
        "bottom" : {
          "value" : 30,
          "units" : "px"
        },
        "left" : {
          "value" : 30,
          "units" : "px"
        },
        "right" : {
          "value" : 30,
          "units" : "px"
        }
      }
    }
  } ],
  "tab" : "STYLE",
  "expanded" : false,
  "type" : "group",
  "default" : {
    "corner" : { },
    "boxes_bg" : {
      "bg_color" : {
        "color" : "#ffffff",
        "opacity" : 100
      }
    },
    "boxes_padding" : {
      "padding" : {
        "top" : {
          "value" : 30,
          "units" : "px"
        },
        "bottom" : {
          "value" : 30,
          "units" : "px"
        },
        "left" : {
          "value" : 30,
          "units" : "px"
        },
        "right" : {
          "value" : 30,
          "units" : "px"
        }
      }
    }
  }
} ]